wsds/__init__.py
wsds/wsds.py
wsds-0.0.1.dist-info/LICENSE
wsds-0.0.1.dist-info/METADATA
wsds-0.0.1.dist-info/WHEEL
wsds-0.0.1.dist-info/entry_points.txt
wsds-0.0.1.dist-info/top_level.txt
wsds-0.0.1.dist-info/RECORD
