Metadata-Version: 2.1
Name: wsds
Version: 0.0.1
Summary: A simple framework for building complex web applications.
Author: washudashu
Author-email: washudashu@163.com
Classifier: License :: OSI Approved :: BSD License
Classifier: Operating System :: OS Independent
Classifier: Programming Language :: Python :: 3
Requires-Python: >=2.7, !=3.0.*, !=3.1.*, !=3.2.*, !=3.3.*, !=3.4.*
License-File: LICENSE
Requires-Dist: Werkzeug >=0.15
Requires-Dist: Jinja2 >=2.10.1
Requires-Dist: itsdangerous >=0.24
Requires-Dist: click >=5.1
Provides-Extra: dev
Requires-Dist: pytest ; extra == 'dev'
Requires-Dist: coverage ; extra == 'dev'
Requires-Dist: tox ; extra == 'dev'
Requires-Dist: sphinx ; extra == 'dev'
Requires-Dist: pallets-sphinx-themes ; extra == 'dev'
Requires-Dist: sphinxcontrib-log-cabinet ; extra == 'dev'
Requires-Dist: sphinx-issues ; extra == 'dev'
Provides-Extra: docs
Requires-Dist: sphinx ; extra == 'docs'
Requires-Dist: pallets-sphinx-themes ; extra == 'docs'
Requires-Dist: sphinxcontrib-log-cabinet ; extra == 'docs'
Requires-Dist: sphinx-issues ; extra == 'docs'
Provides-Extra: dotenv
Requires-Dist: python-dotenv ; extra == 'dotenv'
